uipath_llamaindex/__init__.py
uipath_llamaindex/middlewares.py
uipath_llamaindex/_cli/__init__.py
uipath_llamaindex/_cli/cli_new.py
uipath_llamaindex/_cli/_templates/llama_index.json.template
uipath_llamaindex/_cli/_templates/main.py.template
uipath_llamaindex/embeddings/__init__.py
uipath_llamaindex/embeddings/_openai.py
uipath_llamaindex/llms/__init__.py
uipath_llamaindex/llms/_openai.py
uipath_llamaindex/llms/bedrock.py
uipath_llamaindex/llms/supported_models.py
uipath_llamaindex/llms/vertex.py
uipath_llamaindex/models/__init__.py
uipath_llamaindex/models/events.py
uipath_llamaindex/query_engines/__init__.py
uipath_llamaindex/query_engines/context_grounding_query_engine.py
uipath_llamaindex/retrievers/__init__.py
uipath_llamaindex/retrievers/context_grounding_retriever.py
uipath_llamaindex/runtime/__init__.py
uipath_llamaindex/runtime/_serialize.py
uipath_llamaindex/runtime/_sqlite.py
uipath_llamaindex/runtime/_telemetry.py
uipath_llamaindex/runtime/breakpoints.py
uipath_llamaindex/runtime/config.py
uipath_llamaindex/runtime/errors.py
uipath_llamaindex/runtime/factory.py
uipath_llamaindex/runtime/runtime.py
uipath_llamaindex/runtime/schema.py
uipath_llamaindex/runtime/storage.py
uipath_llamaindex/runtime/workflow.py
uipath_llamaindex-0.5.0.dist-info/METADATA
uipath_llamaindex-0.5.0.dist-info/WHEEL
uipath_llamaindex-0.5.0.dist-info/entry_points.txt
uipath_llamaindex-0.5.0.dist-info/RECORD
