Metadata-Version: 2.4
Name: uipath-llamaindex
Version: 0.5.0
Summary: UiPath LlamaIndex SDK
Project-URL: Homepage, https://uipath.com
Project-URL: Repository, https://github.com/UiPath/uipath-integrations-python/tree/main/packages/uipath-llamaindex
Maintainer-email: Marius Cosareanu <marius.cosareanu@uipath.com>, Cristian Pufu <cristian.pufu@uipath.com>
Classifier: Intended Audience :: Developers
Classifier: Programming Language :: Python :: 3.11
Classifier: Programming Language :: Python :: 3.12
Classifier: Programming Language :: Python :: 3.13
Classifier: Topic :: Software Development :: Build Tools
Requires-Python: >=3.11
Requires-Dist: aiosqlite>=0.21.0
Requires-Dist: llama-index-embeddings-azure-openai>=0.4.1
Requires-Dist: llama-index-llms-azure-openai>=0.4.2
Requires-Dist: llama-index>=0.14.8
Requires-Dist: openinference-instrumentation-llama-index>=4.3.9
Requires-Dist: uipath-runtime<0.7.0,>=0.6.0
Requires-Dist: uipath<2.7.0,>=2.6.0
Provides-Extra: bedrock
Requires-Dist: aiobotocore>=2.5.0; extra == 'bedrock'
Requires-Dist: boto3>=1.28.0; extra == 'bedrock'
Requires-Dist: llama-index-llms-bedrock-converse>=0.3.0; extra == 'bedrock'
Requires-Dist: llama-index-llms-bedrock>=0.3.0; extra == 'bedrock'
Provides-Extra: vertex
Requires-Dist: google-genai>=1.0.0; extra == 'vertex'
Requires-Dist: llama-index-llms-google-genai>=0.8.0; extra == 'vertex'
